comment_inspect/__init__.py
comment_inspect/comment_inspect.py
comment_inspect/parsers/__init__.py
comment_inspect/parsers/c_parser.py
comment_inspect/parsers/common.py
comment_inspect/parsers/js_parser.py
comment_inspect/parsers/python_parser.py
comment_inspect-0.1.dist-info/METADATA
comment_inspect-0.1.dist-info/WHEEL
comment_inspect-0.1.dist-info/entry_points.txt
comment_inspect-0.1.dist-info/top_level.txt
comment_inspect-0.1.dist-info/RECORD
