Metadata-Version: 2.1
Name: comment-inspect
Version: 0.1
Summary: Parse comments from various programming languages
Author: Faiz Alam
Author-email: mohdfaizalam53@gmail.com
License: MIT
Requires-Python: >=3.7
Requires-Dist: python-magic-bin >=0.4.14
